client/__init__.py
client/client/__init__.py
client/client/add_contact.py
client/client/del_contact.py
client/client/main_window.py
client/client/main_window_conv.py
client/client/start_dialog.py
client/client/transport.py
client/client/dbase/__init__.py
client/client/dbase/database.py
documentation/__init__.py
documentation/source/__init__.py
documentation/source/conf.py
logs/__init__.py
logs/client_log_config.py
logs/server_log_config.py
unit_tests/__init__.py
unit_tests/test_client.py
unit_tests/test_server.py
utils/__init__.py
utils/config_messages.py
utils/decorators.py
utils/errors.py
utils/metaclasses.py
utils/server_socket_descriptor.py
utils/settings.py
net_mess_client-0.1.2.dist-info/METADATA
net_mess_client-0.1.2.dist-info/WHEEL
net_mess_client-0.1.2.dist-info/top_level.txt
net_mess_client-0.1.2.dist-info/RECORD
